{
  "resourceType": "MeasureReport",
  "id": "aafdf899-5509-446e-915a-986e2426434a",
  "meta": {
    "profile": [ "http://hl7.org/fhir/us/cqfmeasures/StructureDefinition/test-case-cqfm" ]
  },
  "contained": [ {
    "resourceType": "Parameters",
    "id": "26b5387b-41f5-4707-964f-42629993eaac-parameters",
    "parameter": [ {
      "name": "subject",
      "valueString": "eb03b6f2-c098-4428-b31e-96fc9d968947"
    } ]
  } ],
  "extension": [ {
    "url": "http://hl7.org/fhir/StructureDefinition/cqf-inputParameters",
    "valueReference": {
      "reference": "#26b5387b-41f5-4707-964f-42629993eaac-parameters"
    }
  }, {
    "url": "http://hl7.org/fhir/us/cqfmeasures/StructureDefinition/cqfm-testCaseDescription",
    "valueMarkdown": "Screened, At Risk, Referral, Assessed, Not/Mild Malnutrition, No Diagnosis, Nutrition Care Plan"
  } ],
  "modifierExtension": [ {
    "url": "http://hl7.org/fhir/us/cqfmeasures/StructureDefinition/cqfm-isTestCase",
    "valueBoolean": true
  } ],
  "status": "complete",
  "type": "individual",
  "measure": "https://madie.cms.gov/Measure/CMS986FHIRMalnutritionScore",
  "period": {
    "start": "2026-01-01",
    "end": "2026-12-31"
  },
  "group": [ {
    "id": "Group_1",
    "population": [ {
      "id": "InitialPopulation_1",
      "code": {
        "coding": [ {
          "system": "http://terminology.hl7.org/CodeSystem/measure-population",
          "code": "initial-population",
          "display": "Initial Population"
        } ]
      },
      "count": 1
    }, {
      "id": "MeasurePopulation_1",
      "code": {
        "coding": [ {
          "system": "http://terminology.hl7.org/CodeSystem/measure-population",
          "code": "measure-population",
          "display": "Measure Population"
        } ]
      },
      "count": 1
    }, {
      "id": "MeasurePopulationExclusion_1",
      "code": {
        "coding": [ {
          "system": "http://terminology.hl7.org/CodeSystem/measure-population",
          "code": "measure-population-exclusion",
          "display": "Measure Population Exclusion"
        } ]
      },
      "count": 0
    }, {
      "id": "MeasureObservation_1_1",
      "code": {
        "coding": [ {
          "system": "http://terminology.hl7.org/CodeSystem/measure-population",
          "code": "measure-population-observation",
          "display": "Measure Population Observation"
        } ]
      },
      "count": 1
    } ],
    "measureScore": {
      "value": 0.0
    }
  }, {
    "id": "Group_2",
    "population": [ {
      "id": "InitialPopulation_2",
      "code": {
        "coding": [ {
          "system": "http://terminology.hl7.org/CodeSystem/measure-population",
          "code": "initial-population",
          "display": "Initial Population"
        } ]
      },
      "count": 1
    }, {
      "id": "MeasurePopulation_2",
      "code": {
        "coding": [ {
          "system": "http://terminology.hl7.org/CodeSystem/measure-population",
          "code": "measure-population",
          "display": "Measure Population"
        } ]
      },
      "count": 1
    }, {
      "id": "MeasurePopulationExclusion_2",
      "code": {
        "coding": [ {
          "system": "http://terminology.hl7.org/CodeSystem/measure-population",
          "code": "measure-population-exclusion",
          "display": "Measure Population Exclusion"
        } ]
      },
      "count": 0
    }, {
      "id": "MeasureObservation_2_1",
      "code": {
        "coding": [ {
          "system": "http://terminology.hl7.org/CodeSystem/measure-population",
          "code": "measure-population-observation",
          "display": "Measure Population Observation"
        } ]
      },
      "count": 1
    } ],
    "measureScore": {
      "value": 0.0
    }
  }, {
    "id": "Group_3",
    "population": [ {
      "id": "InitialPopulation_3",
      "code": {
        "coding": [ {
          "system": "http://terminology.hl7.org/CodeSystem/measure-population",
          "code": "initial-population",
          "display": "Initial Population"
        } ]
      },
      "count": 1
    }, {
      "id": "MeasurePopulation_3",
      "code": {
        "coding": [ {
          "system": "http://terminology.hl7.org/CodeSystem/measure-population",
          "code": "measure-population",
          "display": "Measure Population"
        } ]
      },
      "count": 1
    }, {
      "id": "MeasurePopulationExclusion_3",
      "code": {
        "coding": [ {
          "system": "http://terminology.hl7.org/CodeSystem/measure-population",
          "code": "measure-population-exclusion",
          "display": "Measure Population Exclusion"
        } ]
      },
      "count": 0
    }, {
      "id": "MeasureObservation_3_1",
      "code": {
        "coding": [ {
          "system": "http://terminology.hl7.org/CodeSystem/measure-population",
          "code": "measure-population-observation",
          "display": "Measure Population Observation"
        } ]
      },
      "count": 0
    } ],
    "measureScore": {
      "value": 0.0
    }
  }, {
    "id": "Group_4",
    "population": [ {
      "id": "InitialPopulation_4",
      "code": {
        "coding": [ {
          "system": "http://terminology.hl7.org/CodeSystem/measure-population",
          "code": "initial-population",
          "display": "Initial Population"
        } ]
      },
      "count": 1
    }, {
      "id": "MeasurePopulation_4",
      "code": {
        "coding": [ {
          "system": "http://terminology.hl7.org/CodeSystem/measure-population",
          "code": "measure-population",
          "display": "Measure Population"
        } ]
      },
      "count": 1
    }, {
      "id": "MeasurePopulationExclusion_4",
      "code": {
        "coding": [ {
          "system": "http://terminology.hl7.org/CodeSystem/measure-population",
          "code": "measure-population-exclusion",
          "display": "Measure Population Exclusion"
        } ]
      },
      "count": 0
    }, {
      "id": "MeasureObservation_4_1",
      "code": {
        "coding": [ {
          "system": "http://terminology.hl7.org/CodeSystem/measure-population",
          "code": "measure-population-observation",
          "display": "Measure Population Observation"
        } ]
      },
      "count": 0
    } ],
    "measureScore": {
      "value": 0.0
    }
  }, {
    "id": "Group_5",
    "population": [ {
      "id": "InitialPopulation_5",
      "code": {
        "coding": [ {
          "system": "http://terminology.hl7.org/CodeSystem/measure-population",
          "code": "initial-population",
          "display": "Initial Population"
        } ]
      },
      "count": 1
    }, {
      "id": "MeasurePopulation_5",
      "code": {
        "coding": [ {
          "system": "http://terminology.hl7.org/CodeSystem/measure-population",
          "code": "measure-population",
          "display": "Measure Population"
        } ]
      },
      "count": 1
    }, {
      "id": "MeasurePopulationExclusion_5",
      "code": {
        "coding": [ {
          "system": "http://terminology.hl7.org/CodeSystem/measure-population",
          "code": "measure-population-exclusion",
          "display": "Measure Population Exclusion"
        } ]
      },
      "count": 0
    }, {
      "id": "MeasureObservation_5_1",
      "code": {
        "coding": [ {
          "system": "http://terminology.hl7.org/CodeSystem/measure-population",
          "code": "measure-population-observation",
          "display": "Measure Population Observation"
        } ]
      },
      "count": 2
    } ],
    "measureScore": {
      "value": 0.0
    }
  }, {
    "id": "Group_6",
    "population": [ {
      "id": "InitialPopulation_6",
      "code": {
        "coding": [ {
          "system": "http://terminology.hl7.org/CodeSystem/measure-population",
          "code": "initial-population",
          "display": "Initial Population"
        } ]
      },
      "count": 1
    }, {
      "id": "MeasurePopulation_6",
      "code": {
        "coding": [ {
          "system": "http://terminology.hl7.org/CodeSystem/measure-population",
          "code": "measure-population",
          "display": "Measure Population"
        } ]
      },
      "count": 1
    }, {
      "id": "MeasurePopulationExclusion_6",
      "code": {
        "coding": [ {
          "system": "http://terminology.hl7.org/CodeSystem/measure-population",
          "code": "measure-population-exclusion",
          "display": "Measure Population Exclusion"
        } ]
      },
      "count": 0
    }, {
      "id": "MeasureObservation_6_1",
      "code": {
        "coding": [ {
          "system": "http://terminology.hl7.org/CodeSystem/measure-population",
          "code": "measure-population-observation",
          "display": "Measure Population Observation"
        } ]
      },
      "count": 100
    } ],
    "measureScore": {
      "value": 0.0
    }
  } ],
  "evaluatedResource": [ {
    "reference": "Patient/eb03b6f2-c098-4428-b31e-96fc9d968947"
  }, {
    "reference": "Encounter/71c85af8-2015-418b-b651-a9ef3966d744"
  }, {
    "reference": "Observation/275b32a8-fb0b-4787-8fd6-dea55f7efb9d"
  }, {
    "reference": "Observation/1f34709d-7bb2-424d-8fa4-1b85801f5649"
  }, {
    "reference": "Procedure/ebd89417-6283-4301-98e5-fc7b23bd7176"
  }, {
    "reference": "Procedure/3d775253-a5c0-4e15-81ab-75004779bbf1"
  }, {
    "reference": "Coverage/14dacccb-d45c-4094-81a4-3280383e79f5"
  }, {
    "reference": "Organization/1584735e-3970-49ec-bf3e-02a2425e67c3"
  } ]
}